{"box_data": [{"position": {"minX": 554.0, "minY": 365.0, "maxX": 562.0, "maxY": 439.0}, "class_id": 0, "box_caption": "bone-loss 0.025", "scores": {"class_score": 0.0253143310546875}, "domain": "pixel"}, {"position": {"minX": 591.5, "minY": 351.0, "maxX": 593.5, "maxY": 558.5}, "class_id": 0, "box_caption": "bone-loss 0.025", "scores": {"class_score": 0.024871826171875}, "domain": "pixel"}, {"position": {"minX": 570.5, "minY": 353.5, "maxX": 572.5, "maxY": 539.0}, "class_id": 0, "box_caption": "bone-loss 0.021", "scores": {"class_score": 0.0214691162109375}, "domain": "pixel"}, {"position": {"minX": 586.0, "minY": 382.5, "maxX": 596.0, "maxY": 481.5}, "class_id": 0, "box_caption": "bone-loss 0.021", "scores": {"class_score": 0.0212860107421875}, "domain": "pixel"}, {"position": {"minX": 338.25, "minY": 205.375, "maxX": 364.75, "maxY": 377.5}, "class_id": 0, "box_caption": "bone-loss 0.018", "scores": {"class_score": 0.01824951171875}, "domain": "pixel"}, {"position": {"minX": 554.0, "minY": 341.0, "maxX": 561.0, "maxY": 427.5}, "class_id": 0, "box_caption": "bone-loss 0.017", "scores": {"class_score": 0.017486572265625}, "domain": "pixel"}, {"position": {"minX": 352.5, "minY": 300.0, "maxX": 356.5, "maxY": 336.0}, "class_id": 0, "box_caption": "bone-loss 0.017", "scores": {"class_score": 0.01715087890625}, "domain": "pixel"}, {"position": {"minX": 574.5, "minY": 397.25, "maxX": 578.5, "maxY": 532.5}, "class_id": 0, "box_caption": "bone-loss 0.017", "scores": {"class_score": 0.016937255859375}, "domain": "pixel"}, {"position": {"minX": 592.0, "minY": 372.0, "maxX": 595.0, "maxY": 566.5}, "class_id": 0, "box_caption": "bone-loss 0.016", "scores": {"class_score": 0.016357421875}, "domain": "pixel"}, {"position": {"minX": 571.5, "minY": 351.0, "maxX": 576.5, "maxY": 452.0}, "class_id": 0, "box_caption": "bone-loss 0.016", "scores": {"class_score": 0.0158843994140625}, "domain": "pixel"}, {"position": {"minX": 361.5, "minY": 343.75, "maxX": 363.5, "maxY": 446.75}, "class_id": 0, "box_caption": "bone-loss 0.015", "scores": {"class_score": 0.01483154296875}, "domain": "pixel"}, {"position": {"minX": 604.0, "minY": 392.25, "maxX": 609.0, "maxY": 525.0}, "class_id": 0, "box_caption": "bone-loss 0.014", "scores": {"class_score": 0.01404571533203125}, "domain": "pixel"}, {"position": {"minX": 538.0, "minY": 390.0, "maxX": 540.0, "maxY": 531.5}, "class_id": 0, "box_caption": "bone-loss 0.013", "scores": {"class_score": 0.0131072998046875}, "domain": "pixel"}, {"position": {"minX": 551.0, "minY": 384.5, "maxX": 567.0, "maxY": 450.5}, "class_id": 0, "box_caption": "bone-loss 0.012", "scores": {"class_score": 0.011688232421875}, "domain": "pixel"}, {"position": {"minX": 570.5, "minY": 342.75, "maxX": 572.5, "maxY": 425.75}, "class_id": 0, "box_caption": "bone-loss 0.012", "scores": {"class_score": 0.01166534423828125}, "domain": "pixel"}, {"position": {"minX": 600.5, "minY": 389.0, "maxX": 609.5, "maxY": 481.0}, "class_id": 0, "box_caption": "bone-loss 0.012", "scores": {"class_score": 0.01166534423828125}, "domain": "pixel"}, {"position": {"minX": 333.75, "minY": 286.0, "maxX": 341.25, "maxY": 348.0}, "class_id": 0, "box_caption": "bone-loss 0.011", "scores": {"class_score": 0.01123046875}, "domain": "pixel"}, {"position": {"minX": 351.25, "minY": 329.25, "maxX": 358.25, "maxY": 341.75}, "class_id": 0, "box_caption": "bone-loss 0.011", "scores": {"class_score": 0.0109710693359375}, "domain": "pixel"}, {"position": {"minX": 352.0, "minY": 271.75, "maxX": 360.5, "maxY": 333.75}, "class_id": 0, "box_caption": "bone-loss 0.011", "scores": {"class_score": 0.01067352294921875}, "domain": "pixel"}, {"position": {"minX": 334.0, "minY": 318.5, "maxX": 341.5, "maxY": 352.0}, "class_id": 0, "box_caption": "bone-loss 0.011", "scores": {"class_score": 0.01062774658203125}, "domain": "pixel"}, {"position": {"minX": 377.25, "minY": 335.75, "maxX": 378.75, "maxY": 453.25}, "class_id": 0, "box_caption": "bone-loss 0.010", "scores": {"class_score": 0.0104217529296875}, "domain": "pixel"}, {"position": {"minX": 365.0, "minY": 256.25, "maxX": 379.0, "maxY": 331.75}, "class_id": 0, "box_caption": "bone-loss 0.010", "scores": {"class_score": 0.0102386474609375}, "domain": "pixel"}, {"position": {"minX": 369.75, "minY": 322.5, "maxX": 372.75, "maxY": 326.0}, "class_id": 0, "box_caption": "bone-loss 0.010", "scores": {"class_score": 0.01023101806640625}, "domain": "pixel"}, {"position": {"minX": 362.5, "minY": 353.75, "maxX": 366.5, "maxY": 471.75}, "class_id": 0, "box_caption": "bone-loss 0.010", "scores": {"class_score": 0.01006317138671875}, "domain": "pixel"}, {"position": {"minX": 431.25, "minY": 401.0, "maxX": 444.25, "maxY": 523.0}, "class_id": 0, "box_caption": "bone-loss 0.010", "scores": {"class_score": 0.00977325439453125}, "domain": "pixel"}, {"position": {"minX": 564.0, "minY": 385.75, "maxX": 573.0, "maxY": 470.75}, "class_id": 0, "box_caption": "bone-loss 0.009", "scores": {"class_score": 0.00946807861328125}, "domain": "pixel"}, {"position": {"minX": 196.75, "minY": 270.5, "maxX": 241.75, "maxY": 296.5}, "class_id": 1, "box_caption": "dental-caries 0.009", "scores": {"class_score": 0.00925445556640625}, "domain": "pixel"}, {"position": {"minX": 605.5, "minY": 388.0, "maxX": 610.5, "maxY": 555.5}, "class_id": 0, "box_caption": "bone-loss 0.009", "scores": {"class_score": 0.00904083251953125}, "domain": "pixel"}, {"position": {"minX": 335.0, "minY": 308.75, "maxX": 393.5, "maxY": 498.75}, "class_id": 1, "box_caption": "dental-caries 0.009", "scores": {"class_score": 0.00861358642578125}, "domain": "pixel"}, {"position": {"minX": 549.5, "minY": 341.0, "maxX": 553.5, "maxY": 551.5}, "class_id": 0, "box_caption": "bone-loss 0.008", "scores": {"class_score": 0.0084686279296875}, "domain": "pixel"}, {"position": {"minX": -79.875, "minY": 169.0, "maxX": 493.5, "maxY": 448.0}, "class_id": 0, "box_caption": "bone-loss 0.008", "scores": {"class_score": 0.00833892822265625}, "domain": "pixel"}, {"position": {"minX": 419.75, "minY": 402.0, "maxX": 429.75, "maxY": 522.5}, "class_id": 0, "box_caption": "bone-loss 0.008", "scores": {"class_score": 0.00820159912109375}, "domain": "pixel"}, {"position": {"minX": 378.5, "minY": 343.5, "maxX": 384.5, "maxY": 485.5}, "class_id": 0, "box_caption": "bone-loss 0.008", "scores": {"class_score": 0.008148193359375}, "domain": "pixel"}, {"position": {"minX": 291.0, "minY": 243.875, "maxX": 366.0, "maxY": 565.0}, "class_id": 1, "box_caption": "dental-caries 0.008", "scores": {"class_score": 0.008148193359375}, "domain": "pixel"}, {"position": {"minX": 605.5, "minY": 393.0, "maxX": 631.5, "maxY": 479.5}, "class_id": 0, "box_caption": "bone-loss 0.008", "scores": {"class_score": 0.008087158203125}, "domain": "pixel"}, {"position": {"minX": 356.25, "minY": 313.25, "maxX": 436.25, "maxY": 496.25}, "class_id": 1, "box_caption": "dental-caries 0.008", "scores": {"class_score": 0.00800323486328125}, "domain": "pixel"}, {"position": {"minX": 558.0, "minY": 387.5, "maxX": 560.0, "maxY": 538.5}, "class_id": 0, "box_caption": "bone-loss 0.008", "scores": {"class_score": 0.00791168212890625}, "domain": "pixel"}, {"position": {"minX": 349.0, "minY": 347.25, "maxX": 358.5, "maxY": 364.75}, "class_id": 0, "box_caption": "bone-loss 0.008", "scores": {"class_score": 0.007648468017578125}, "domain": "pixel"}, {"position": {"minX": 346.5, "minY": 323.0, "maxX": 351.0, "maxY": 471.0}, "class_id": 0, "box_caption": "bone-loss 0.008", "scores": {"class_score": 0.007568359375}, "domain": "pixel"}, {"position": {"minX": 422.25, "minY": 377.25, "maxX": 492.75, "maxY": 570.5}, "class_id": 1, "box_caption": "dental-caries 0.008", "scores": {"class_score": 0.007537841796875}, "domain": "pixel"}, {"position": {"minX": 530.0, "minY": 346.75, "maxX": 546.0, "maxY": 419.75}, "class_id": 0, "box_caption": "bone-loss 0.007", "scores": {"class_score": 0.007450103759765625}, "domain": "pixel"}, {"position": {"minX": 366.25, "minY": 178.0, "maxX": 509.75, "maxY": 506.0}, "class_id": 1, "box_caption": "dental-caries 0.007", "scores": {"class_score": 0.007427215576171875}, "domain": "pixel"}, {"position": {"minX": 580.5, "minY": 426.75, "maxX": 613.5, "maxY": 470.75}, "class_id": 1, "box_caption": "dental-caries 0.007", "scores": {"class_score": 0.00737762451171875}, "domain": "pixel"}, {"position": {"minX": 331.75, "minY": 218.0, "maxX": 385.75, "maxY": 515.0}, "class_id": 1, "box_caption": "dental-caries 0.007", "scores": {"class_score": 0.007366180419921875}, "domain": "pixel"}, {"position": {"minX": 545.5, "minY": 380.25, "maxX": 565.5, "maxY": 483.25}, "class_id": 0, "box_caption": "bone-loss 0.007", "scores": {"class_score": 0.007293701171875}, "domain": "pixel"}, {"position": {"minX": 196.75, "minY": 270.5, "maxX": 241.75, "maxY": 296.5}, "class_id": 0, "box_caption": "bone-loss 0.007", "scores": {"class_score": 0.00724029541015625}, "domain": "pixel"}, {"position": {"minX": 609.5, "minY": 410.25, "maxX": 625.5, "maxY": 503.75}, "class_id": 0, "box_caption": "bone-loss 0.007", "scores": {"class_score": 0.007221221923828125}, "domain": "pixel"}, {"position": {"minX": 314.5, "minY": 181.0, "maxX": 339.0, "maxY": 410.0}, "class_id": 0, "box_caption": "bone-loss 0.007", "scores": {"class_score": 0.00717926025390625}, "domain": "pixel"}, {"position": {"minX": 448.0, "minY": 324.75, "maxX": 545.0, "maxY": 560.0}, "class_id": 1, "box_caption": "dental-caries 0.007", "scores": {"class_score": 0.007175445556640625}, "domain": "pixel"}, {"position": {"minX": 534.0, "minY": 370.75, "maxX": 548.0, "maxY": 426.75}, "class_id": 0, "box_caption": "bone-loss 0.007", "scores": {"class_score": 0.007137298583984375}, "domain": "pixel"}, {"position": {"minX": 449.75, "minY": 422.75, "maxX": 452.75, "maxY": 505.25}, "class_id": 0, "box_caption": "bone-loss 0.007", "scores": {"class_score": 0.007083892822265625}, "domain": "pixel"}, {"position": {"minX": 256.25, "minY": 34.75, "maxX": 303.25, "maxY": 390.25}, "class_id": 0, "box_caption": "bone-loss 0.007", "scores": {"class_score": 0.00702667236328125}, "domain": "pixel"}, {"position": {"minX": 570.0, "minY": 373.75, "maxX": 580.0, "maxY": 459.75}, "class_id": 0, "box_caption": "bone-loss 0.007", "scores": {"class_score": 0.007022857666015625}, "domain": "pixel"}, {"position": {"minX": 264.5, "minY": 182.0, "maxX": 325.5, "maxY": 626.0}, "class_id": 1, "box_caption": "dental-caries 0.007", "scores": {"class_score": 0.0070037841796875}, "domain": "pixel"}, {"position": {"minX": 291.0, "minY": 243.875, "maxX": 366.0, "maxY": 565.0}, "class_id": 0, "box_caption": "bone-loss 0.007", "scores": {"class_score": 0.006999969482421875}, "domain": "pixel"}, {"position": {"minX": 448.5, "minY": 381.75, "maxX": 455.0, "maxY": 507.75}, "class_id": 0, "box_caption": "bone-loss 0.007", "scores": {"class_score": 0.006916046142578125}, "domain": "pixel"}, {"position": {"minX": 112.8125, "minY": 231.5, "maxX": 355.5, "maxY": 401.0}, "class_id": 1, "box_caption": "dental-caries 0.007", "scores": {"class_score": 0.0069122314453125}, "domain": "pixel"}, {"position": {"minX": 518.5, "minY": 368.25, "maxX": 523.5, "maxY": 553.5}, "class_id": 0, "box_caption": "bone-loss 0.007", "scores": {"class_score": 0.00685882568359375}, "domain": "pixel"}, {"position": {"minX": 433.25, "minY": 383.25, "maxX": 442.75, "maxY": 574.0}, "class_id": 0, "box_caption": "bone-loss 0.007", "scores": {"class_score": 0.006778717041015625}, "domain": "pixel"}, {"position": {"minX": 187.0, "minY": 290.25, "maxX": 241.25, "maxY": 311.25}, "class_id": 1, "box_caption": "dental-caries 0.007", "scores": {"class_score": 0.00673675537109375}, "domain": "pixel"}, {"position": {"minX": 264.5, "minY": 182.0, "maxX": 325.5, "maxY": 626.0}, "class_id": 0, "box_caption": "bone-loss 0.007", "scores": {"class_score": 0.0065460205078125}, "domain": "pixel"}, {"position": {"minX": 367.75, "minY": 342.75, "maxX": 370.75, "maxY": 344.25}, "class_id": 0, "box_caption": "bone-loss 0.007", "scores": {"class_score": 0.006504058837890625}, "domain": "pixel"}, {"position": {"minX": 325.5, "minY": 261.5, "maxX": 345.5, "maxY": 347.5}, "class_id": 0, "box_caption": "bone-loss 0.006", "scores": {"class_score": 0.00649261474609375}, "domain": "pixel"}, {"position": {"minX": 509.0, "minY": 304.0, "maxX": 519.0, "maxY": 410.0}, "class_id": 0, "box_caption": "bone-loss 0.006", "scores": {"class_score": 0.0064849853515625}, "domain": "pixel"}, {"position": {"minX": 311.25, "minY": 181.5, "maxX": 379.25, "maxY": 351.5}, "class_id": 0, "box_caption": "bone-loss 0.006", "scores": {"class_score": 0.0064544677734375}, "domain": "pixel"}, {"position": {"minX": 331.0, "minY": 301.0, "maxX": 374.5, "maxY": 345.5}, "class_id": 0, "box_caption": "bone-loss 0.006", "scores": {"class_score": 0.006427764892578125}, "domain": "pixel"}, {"position": {"minX": 569.0, "minY": 390.5, "maxX": 580.0, "maxY": 583.0}, "class_id": 0, "box_caption": "bone-loss 0.006", "scores": {"class_score": 0.006420135498046875}, "domain": "pixel"}, {"position": {"minX": 208.5, "minY": 88.625, "maxX": 280.5, "maxY": 340.0}, "class_id": 0, "box_caption": "bone-loss 0.006", "scores": {"class_score": 0.00641632080078125}, "domain": "pixel"}, {"position": {"minX": 416.0, "minY": 375.5, "maxX": 430.0, "maxY": 518.5}, "class_id": 0, "box_caption": "bone-loss 0.006", "scores": {"class_score": 0.006404876708984375}, "domain": "pixel"}, {"position": {"minX": 184.75, "minY": 157.25, "maxX": 229.0, "maxY": 344.25}, "class_id": 1, "box_caption": "dental-caries 0.006", "scores": {"class_score": 0.006404876708984375}, "domain": "pixel"}, {"position": {"minX": 356.25, "minY": 313.25, "maxX": 436.25, "maxY": 496.25}, "class_id": 0, "box_caption": "bone-loss 0.006", "scores": {"class_score": 0.006366729736328125}, "domain": "pixel"}, {"position": {"minX": 335.0, "minY": 308.75, "maxX": 393.5, "maxY": 498.75}, "class_id": 0, "box_caption": "bone-loss 0.006", "scores": {"class_score": 0.006359100341796875}, "domain": "pixel"}, {"position": {"minX": 426.5, "minY": 88.6875, "maxX": 568.0, "maxY": 329.0}, "class_id": 0, "box_caption": "bone-loss 0.006", "scores": {"class_score": 0.006290435791015625}, "domain": "pixel"}, {"position": {"minX": -125.75, "minY": 139.875, "maxX": 546.0, "maxY": 344.5}, "class_id": 0, "box_caption": "bone-loss 0.006", "scores": {"class_score": 0.0062713623046875}, "domain": "pixel"}, {"position": {"minX": 414.5, "minY": 321.5, "maxX": 415.0, "maxY": 341.0}, "class_id": 0, "box_caption": "bone-loss 0.006", "scores": {"class_score": 0.006195068359375}, "domain": "pixel"}, {"position": {"minX": 229.0, "minY": 353.0, "maxX": 426.0, "maxY": 588.0}, "class_id": 1, "box_caption": "dental-caries 0.006", "scores": {"class_score": 0.006175994873046875}, "domain": "pixel"}, {"position": {"minX": 365.5, "minY": 355.75, "maxX": 371.0, "maxY": 362.25}, "class_id": 0, "box_caption": "bone-loss 0.006", "scores": {"class_score": 0.006122589111328125}, "domain": "pixel"}, {"position": {"minX": 594.5, "minY": 446.75, "maxX": 626.5, "maxY": 488.25}, "class_id": 1, "box_caption": "dental-caries 0.006", "scores": {"class_score": 0.006107330322265625}, "domain": "pixel"}, {"position": {"minX": 375.25, "minY": 279.0, "maxX": 472.75, "maxY": 533.0}, "class_id": 1, "box_caption": "dental-caries 0.006", "scores": {"class_score": 0.00605010986328125}, "domain": "pixel"}, {"position": {"minX": -87.1875, "minY": 13.875, "maxX": 309.5, "maxY": 280.0}, "class_id": 1, "box_caption": "dental-caries 0.006", "scores": {"class_score": 0.0060272216796875}, "domain": "pixel"}, {"position": {"minX": 265.0, "minY": 88.125, "maxX": 289.0, "maxY": 404.0}, "class_id": 1, "box_caption": "dental-caries 0.006", "scores": {"class_score": 0.006000518798828125}, "domain": "pixel"}, {"position": {"minX": 353.25, "minY": 224.125, "maxX": 377.75, "maxY": 341.0}, "class_id": 0, "box_caption": "bone-loss 0.006", "scores": {"class_score": 0.005977630615234375}, "domain": "pixel"}, {"position": {"minX": 191.75, "minY": 261.5, "maxX": 257.5, "maxY": 276.0}, "class_id": 0, "box_caption": "bone-loss 0.006", "scores": {"class_score": 0.0059661865234375}, "domain": "pixel"}, {"position": {"minX": 414.5, "minY": 102.125, "maxX": 520.5, "maxY": 373.0}, "class_id": 0, "box_caption": "bone-loss 0.006", "scores": {"class_score": 0.005950927734375}, "domain": "pixel"}, {"position": {"minX": 582.5, "minY": 385.0, "maxX": 598.5, "maxY": 450.5}, "class_id": 0, "box_caption": "bone-loss 0.006", "scores": {"class_score": 0.0059051513671875}, "domain": "pixel"}, {"position": {"minX": 184.75, "minY": 157.25, "maxX": 229.0, "maxY": 344.25}, "class_id": 0, "box_caption": "bone-loss 0.006", "scores": {"class_score": 0.005893707275390625}, "domain": "pixel"}, {"position": {"minX": 50.125, "minY": 97.75, "maxX": 430.5, "maxY": 535.0}, "class_id": 0, "box_caption": "bone-loss 0.006", "scores": {"class_score": 0.005870819091796875}, "domain": "pixel"}, {"position": {"minX": 347.5, "minY": 108.0, "maxX": 461.5, "maxY": 498.5}, "class_id": 1, "box_caption": "dental-caries 0.006", "scores": {"class_score": 0.005847930908203125}, "domain": "pixel"}, {"position": {"minX": 370.5, "minY": 302.0, "maxX": 376.5, "maxY": 315.0}, "class_id": 0, "box_caption": "bone-loss 0.006", "scores": {"class_score": 0.0058441162109375}, "domain": "pixel"}, {"position": {"minX": 384.5, "minY": 300.0, "maxX": 385.0, "maxY": 488.5}, "class_id": 0, "box_caption": "bone-loss 0.006", "scores": {"class_score": 0.005840301513671875}, "domain": "pixel"}, {"position": {"minX": 421.0, "minY": 357.0, "maxX": 441.5, "maxY": 536.5}, "class_id": 0, "box_caption": "bone-loss 0.006", "scores": {"class_score": 0.005802154541015625}, "domain": "pixel"}, {"position": {"minX": 399.5, "minY": 326.25, "maxX": 400.0, "maxY": 335.75}, "class_id": 0, "box_caption": "bone-loss 0.006", "scores": {"class_score": 0.005794525146484375}, "domain": "pixel"}, {"position": {"minX": 406.5, "minY": 321.0, "maxX": 408.5, "maxY": 504.5}, "class_id": 0, "box_caption": "bone-loss 0.006", "scores": {"class_score": 0.00579071044921875}, "domain": "pixel"}, {"position": {"minX": 580.5, "minY": 426.75, "maxX": 613.5, "maxY": 470.75}, "class_id": 0, "box_caption": "bone-loss 0.006", "scores": {"class_score": 0.00577545166015625}, "domain": "pixel"}, {"position": {"minX": 414.5, "minY": 102.125, "maxX": 520.5, "maxY": 373.0}, "class_id": 1, "box_caption": "dental-caries 0.006", "scores": {"class_score": 0.00577545166015625}, "domain": "pixel"}, {"position": {"minX": 464.25, "minY": 321.25, "maxX": 496.75, "maxY": 382.25}, "class_id": 0, "box_caption": "bone-loss 0.006", "scores": {"class_score": 0.005771636962890625}, "domain": "pixel"}, {"position": {"minX": 467.75, "minY": 413.5, "maxX": 470.25, "maxY": 509.5}, "class_id": 0, "box_caption": "bone-loss 0.006", "scores": {"class_score": 0.00574493408203125}, "domain": "pixel"}, {"position": {"minX": 149.75, "minY": 56.0, "maxX": 266.5, "maxY": 376.5}, "class_id": 0, "box_caption": "bone-loss 0.006", "scores": {"class_score": 0.00574493408203125}, "domain": "pixel"}, {"position": {"minX": 593.5, "minY": 432.5, "maxX": 627.5, "maxY": 475.0}, "class_id": 1, "box_caption": "dental-caries 0.006", "scores": {"class_score": 0.0057220458984375}, "domain": "pixel"}, {"position": {"minX": 256.25, "minY": 34.75, "maxX": 303.25, "maxY": 390.25}, "class_id": 1, "box_caption": "dental-caries 0.006", "scores": {"class_score": 0.005706787109375}, "domain": "pixel"}, {"position": {"minX": 385.5, "minY": 326.5, "maxX": 386.5, "maxY": 330.5}, "class_id": 0, "box_caption": "bone-loss 0.006", "scores": {"class_score": 0.005695343017578125}, "domain": "pixel"}, {"position": {"minX": 413.5, "minY": 321.25, "maxX": 510.5, "maxY": 557.0}, "class_id": 1, "box_caption": "dental-caries 0.006", "scores": {"class_score": 0.005695343017578125}, "domain": "pixel"}, {"position": {"minX": 64.9375, "minY": 167.25, "maxX": 266.5, "maxY": 336.75}, "class_id": 1, "box_caption": "dental-caries 0.006", "scores": {"class_score": 0.0056915283203125}, "domain": "pixel"}, {"position": {"minX": 473.0, "minY": 309.75, "maxX": 508.0, "maxY": 360.75}, "class_id": 1, "box_caption": "dental-caries 0.006", "scores": {"class_score": 0.005664825439453125}, "domain": "pixel"}, {"position": {"minX": 226.625, "minY": 183.5, "maxX": 292.0, "maxY": 627.5}, "class_id": 1, "box_caption": "dental-caries 0.006", "scores": {"class_score": 0.0056610107421875}, "domain": "pixel"}, {"position": {"minX": 291.25, "minY": 401.25, "maxX": 301.75, "maxY": 438.25}, "class_id": 0, "box_caption": "bone-loss 0.006", "scores": {"class_score": 0.00565338134765625}, "domain": "pixel"}, {"position": {"minX": 255.0, "minY": 156.25, "maxX": 308.5, "maxY": 396.75}, "class_id": 1, "box_caption": "dental-caries 0.006", "scores": {"class_score": 0.00563812255859375}, "domain": "pixel"}, {"position": {"minX": 329.75, "minY": 379.5, "maxX": 338.75, "maxY": 450.5}, "class_id": 0, "box_caption": "bone-loss 0.006", "scores": {"class_score": 0.005626678466796875}, "domain": "pixel"}, {"position": {"minX": 235.625, "minY": 159.75, "maxX": 255.375, "maxY": 326.25}, "class_id": 1, "box_caption": "dental-caries 0.006", "scores": {"class_score": 0.005619049072265625}, "domain": "pixel"}, {"position": {"minX": 414.75, "minY": 402.25, "maxX": 428.75, "maxY": 555.0}, "class_id": 0, "box_caption": "bone-loss 0.006", "scores": {"class_score": 0.005588531494140625}, "domain": "pixel"}, {"position": {"minX": 358.25, "minY": 393.75, "maxX": 366.75, "maxY": 468.75}, "class_id": 0, "box_caption": "bone-loss 0.006", "scores": {"class_score": 0.0055694580078125}, "domain": "pixel"}, {"position": {"minX": 536.5, "minY": 386.25, "maxX": 540.5, "maxY": 574.0}, "class_id": 0, "box_caption": "bone-loss 0.005", "scores": {"class_score": 0.00548553466796875}, "domain": "pixel"}, {"position": {"minX": 330.75, "minY": 338.75, "maxX": 340.75, "maxY": 372.25}, "class_id": 0, "box_caption": "bone-loss 0.005", "scores": {"class_score": 0.0053863525390625}, "domain": "pixel"}, {"position": {"minX": 584.5, "minY": 395.25, "maxX": 592.5, "maxY": 582.0}, "class_id": 0, "box_caption": "bone-loss 0.005", "scores": {"class_score": 0.005374908447265625}, "domain": "pixel"}, {"position": {"minX": 333.25, "minY": 326.0, "maxX": 369.75, "maxY": 352.0}, "class_id": 0, "box_caption": "bone-loss 0.005", "scores": {"class_score": 0.005367279052734375}, "domain": "pixel"}, {"position": {"minX": 612.0, "minY": 429.5, "maxX": 622.0, "maxY": 513.0}, "class_id": 0, "box_caption": "bone-loss 0.005", "scores": {"class_score": 0.005352020263671875}, "domain": "pixel"}, {"position": {"minX": 529.5, "minY": 312.0, "maxX": 538.5, "maxY": 427.5}, "class_id": 0, "box_caption": "bone-loss 0.005", "scores": {"class_score": 0.00534820556640625}, "domain": "pixel"}, {"position": {"minX": 448.0, "minY": 324.75, "maxX": 545.0, "maxY": 560.0}, "class_id": 0, "box_caption": "bone-loss 0.005", "scores": {"class_score": 0.00534820556640625}, "domain": "pixel"}, {"position": {"minX": 191.75, "minY": 261.5, "maxX": 257.5, "maxY": 276.0}, "class_id": 1, "box_caption": "dental-caries 0.005", "scores": {"class_score": 0.005344390869140625}, "domain": "pixel"}, {"position": {"minX": 331.0, "minY": 301.0, "maxX": 374.5, "maxY": 345.5}, "class_id": 1, "box_caption": "dental-caries 0.005", "scores": {"class_score": 0.005329132080078125}, "domain": "pixel"}, {"position": {"minX": 226.625, "minY": 183.5, "maxX": 292.0, "maxY": 627.5}, "class_id": 0, "box_caption": "bone-loss 0.005", "scores": {"class_score": 0.005321502685546875}, "domain": "pixel"}, {"position": {"minX": 495.5, "minY": 278.75, "maxX": 517.0, "maxY": 356.25}, "class_id": 1, "box_caption": "dental-caries 0.005", "scores": {"class_score": 0.00531005859375}, "domain": "pixel"}, {"position": {"minX": 424.75, "minY": 350.0, "maxX": 428.25, "maxY": 476.5}, "class_id": 0, "box_caption": "bone-loss 0.005", "scores": {"class_score": 0.00531005859375}, "domain": "pixel"}, {"position": {"minX": 117.8125, "minY": 208.0, "maxX": 225.0, "maxY": 409.0}, "class_id": 0, "box_caption": "bone-loss 0.005", "scores": {"class_score": 0.005275726318359375}, "domain": "pixel"}, {"position": {"minX": 417.75, "minY": 295.0, "maxX": 418.75, "maxY": 328.5}, "class_id": 0, "box_caption": "bone-loss 0.005", "scores": {"class_score": 0.00525665283203125}, "domain": "pixel"}, {"position": {"minX": 480.25, "minY": 283.0, "maxX": 662.0, "maxY": 665.0}, "class_id": 1, "box_caption": "dental-caries 0.005", "scores": {"class_score": 0.0052490234375}, "domain": "pixel"}, {"position": {"minX": 355.75, "minY": 326.75, "maxX": 426.75, "maxY": 356.75}, "class_id": 1, "box_caption": "dental-caries 0.005", "scores": {"class_score": 0.005245208740234375}, "domain": "pixel"}, {"position": {"minX": 316.0, "minY": 108.5, "maxX": 363.5, "maxY": 504.5}, "class_id": 1, "box_caption": "dental-caries 0.005", "scores": {"class_score": 0.005222320556640625}, "domain": "pixel"}, {"position": {"minX": 327.25, "minY": 116.0, "maxX": 397.75, "maxY": 481.5}, "class_id": 1, "box_caption": "dental-caries 0.005", "scores": {"class_score": 0.005207061767578125}, "domain": "pixel"}, {"position": {"minX": 370.0, "minY": 110.875, "maxX": 508.5, "maxY": 497.5}, "class_id": 0, "box_caption": "bone-loss 0.005", "scores": {"class_score": 0.0052032470703125}, "domain": "pixel"}, {"position": {"minX": -113.375, "minY": 191.5, "maxX": 448.0, "maxY": 371.5}, "class_id": 0, "box_caption": "bone-loss 0.005", "scores": {"class_score": 0.00518035888671875}, "domain": "pixel"}, {"position": {"minX": 452.5, "minY": 97.125, "maxX": 536.5, "maxY": 393.0}, "class_id": 1, "box_caption": "dental-caries 0.005", "scores": {"class_score": 0.005161285400390625}, "domain": "pixel"}, {"position": {"minX": 466.5, "minY": 291.25, "maxX": 506.0, "maxY": 344.75}, "class_id": 1, "box_caption": "dental-caries 0.005", "scores": {"class_score": 0.005157470703125}, "domain": "pixel"}, {"position": {"minX": 179.75, "minY": 291.75, "maxX": 271.75, "maxY": 311.75}, "class_id": 1, "box_caption": "dental-caries 0.005", "scores": {"class_score": 0.005123138427734375}, "domain": "pixel"}, {"position": {"minX": 452.5, "minY": 97.125, "maxX": 536.5, "maxY": 393.0}, "class_id": 0, "box_caption": "bone-loss 0.005", "scores": {"class_score": 0.00511932373046875}, "domain": "pixel"}, {"position": {"minX": 357.25, "minY": 307.5, "maxX": 464.25, "maxY": 337.0}, "class_id": 0, "box_caption": "bone-loss 0.005", "scores": {"class_score": 0.005077362060546875}, "domain": "pixel"}, {"position": {"minX": 175.875, "minY": 206.875, "maxX": 233.375, "maxY": 358.0}, "class_id": 1, "box_caption": "dental-caries 0.005", "scores": {"class_score": 0.005035400390625}, "domain": "pixel"}, {"position": {"minX": 54.46875, "minY": 303.0, "maxX": 169.0, "maxY": 562.5}, "class_id": 0, "box_caption": "bone-loss 0.005", "scores": {"class_score": 0.005023956298828125}, "domain": "pixel"}, {"position": {"minX": 400.0, "minY": 405.0, "maxX": 419.5, "maxY": 549.5}, "class_id": 0, "box_caption": "bone-loss 0.005", "scores": {"class_score": 0.00499725341796875}, "domain": "pixel"}, {"position": {"minX": -148.0, "minY": -61.875, "maxX": 371.0, "maxY": 302.0}, "class_id": 1, "box_caption": "dental-caries 0.005", "scores": {"class_score": 0.0049896240234375}, "domain": "pixel"}, {"position": {"minX": 48.3125, "minY": 239.375, "maxX": 221.75, "maxY": 331.75}, "class_id": 1, "box_caption": "dental-caries 0.005", "scores": {"class_score": 0.004962921142578125}, "domain": "pixel"}, {"position": {"minX": 375.25, "minY": 279.0, "maxX": 472.75, "maxY": 533.0}, "class_id": 0, "box_caption": "bone-loss 0.005", "scores": {"class_score": 0.00495147705078125}, "domain": "pixel"}, {"position": {"minX": 119.5, "minY": 105.625, "maxX": 241.0, "maxY": 325.0}, "class_id": 0, "box_caption": "bone-loss 0.005", "scores": {"class_score": 0.00494384765625}, "domain": "pixel"}, {"position": {"minX": 50.125, "minY": 97.75, "maxX": 430.5, "maxY": 535.0}, "class_id": 1, "box_caption": "dental-caries 0.005", "scores": {"class_score": 0.00493621826171875}, "domain": "pixel"}, {"position": {"minX": 95.375, "minY": 134.5, "maxX": 194.625, "maxY": 306.75}, "class_id": 0, "box_caption": "bone-loss 0.005", "scores": {"class_score": 0.00492095947265625}, "domain": "pixel"}, {"position": {"minX": 421.25, "minY": 371.0, "maxX": 551.5, "maxY": 636.5}, "class_id": 1, "box_caption": "dental-caries 0.005", "scores": {"class_score": 0.00492095947265625}, "domain": "pixel"}, {"position": {"minX": 238.25, "minY": 0.5, "maxX": 313.25, "maxY": 363.25}, "class_id": 0, "box_caption": "bone-loss 0.005", "scores": {"class_score": 0.004913330078125}, "domain": "pixel"}, {"position": {"minX": 426.5, "minY": 88.6875, "maxX": 568.0, "maxY": 329.0}, "class_id": 1, "box_caption": "dental-caries 0.005", "scores": {"class_score": 0.004909515380859375}, "domain": "pixel"}, {"position": {"minX": 293.25, "minY": 382.75, "maxX": 309.25, "maxY": 426.25}, "class_id": 0, "box_caption": "bone-loss 0.005", "scores": {"class_score": 0.00490570068359375}, "domain": "pixel"}, {"position": {"minX": 255.75, "minY": -30.375, "maxX": 351.25, "maxY": 390.0}, "class_id": 0, "box_caption": "bone-loss 0.005", "scores": {"class_score": 0.00489044189453125}, "domain": "pixel"}, {"position": {"minX": 486.0, "minY": 316.75, "maxX": 567.0, "maxY": 562.0}, "class_id": 1, "box_caption": "dental-caries 0.005", "scores": {"class_score": 0.004886627197265625}, "domain": "pixel"}, {"position": {"minX": 576.5, "minY": 443.5, "maxX": 616.5, "maxY": 487.5}, "class_id": 1, "box_caption": "dental-caries 0.005", "scores": {"class_score": 0.00487518310546875}, "domain": "pixel"}, {"position": {"minX": 149.75, "minY": 56.0, "maxX": 266.5, "maxY": 376.5}, "class_id": 1, "box_caption": "dental-caries 0.005", "scores": {"class_score": 0.004871368408203125}, "domain": "pixel"}, {"position": {"minX": 294.0, "minY": 121.8125, "maxX": 326.0, "maxY": 334.0}, "class_id": 0, "box_caption": "bone-loss 0.005", "scores": {"class_score": 0.00484466552734375}, "domain": "pixel"}, {"position": {"minX": 603.0, "minY": 386.75, "maxX": 630.0, "maxY": 454.75}, "class_id": 0, "box_caption": "bone-loss 0.005", "scores": {"class_score": 0.00482177734375}, "domain": "pixel"}, {"position": {"minX": 388.0, "minY": 372.25, "maxX": 466.0, "maxY": 569.0}, "class_id": 1, "box_caption": "dental-caries 0.005", "scores": {"class_score": 0.00481414794921875}, "domain": "pixel"}, {"position": {"minX": 403.75, "minY": 332.0, "maxX": 407.75, "maxY": 460.5}, "class_id": 0, "box_caption": "bone-loss 0.005", "scores": {"class_score": 0.004802703857421875}, "domain": "pixel"}, {"position": {"minX": 333.25, "minY": 326.0, "maxX": 369.75, "maxY": 352.0}, "class_id": 1, "box_caption": "dental-caries 0.005", "scores": {"class_score": 0.004795074462890625}, "domain": "pixel"}, {"position": {"minX": 182.875, "minY": 269.5, "maxX": 228.375, "maxY": 300.5}, "class_id": 1, "box_caption": "dental-caries 0.005", "scores": {"class_score": 0.004787445068359375}, "domain": "pixel"}, {"position": {"minX": 380.5, "minY": 266.75, "maxX": 393.5, "maxY": 317.25}, "class_id": 0, "box_caption": "bone-loss 0.005", "scores": {"class_score": 0.004779815673828125}, "domain": "pixel"}, {"position": {"minX": 386.0, "minY": 333.25, "maxX": 387.0, "maxY": 495.75}, "class_id": 0, "box_caption": "bone-loss 0.005", "scores": {"class_score": 0.0047760009765625}, "domain": "pixel"}, {"position": {"minX": 235.625, "minY": 159.75, "maxX": 255.375, "maxY": 326.25}, "class_id": 0, "box_caption": "bone-loss 0.005", "scores": {"class_score": 0.00476837158203125}, "domain": "pixel"}, {"position": {"minX": 338.25, "minY": 392.25, "maxX": 354.75, "maxY": 472.25}, "class_id": 0, "box_caption": "bone-loss 0.005", "scores": {"class_score": 0.004764556884765625}, "domain": "pixel"}, {"position": {"minX": 594.0, "minY": 388.0, "maxX": 612.0, "maxY": 450.0}, "class_id": 0, "box_caption": "bone-loss 0.005", "scores": {"class_score": 0.004756927490234375}, "domain": "pixel"}, {"position": {"minX": 320.5, "minY": 394.25, "maxX": 335.5, "maxY": 476.25}, "class_id": 0, "box_caption": "bone-loss 0.005", "scores": {"class_score": 0.004756927490234375}, "domain": "pixel"}, {"position": {"minX": 181.875, "minY": 286.0, "maxX": 212.125, "maxY": 319.5}, "class_id": 1, "box_caption": "dental-caries 0.005", "scores": {"class_score": 0.004749298095703125}, "domain": "pixel"}, {"position": {"minX": 354.0, "minY": 317.5, "maxX": 355.5, "maxY": 441.5}, "class_id": 0, "box_caption": "bone-loss 0.005", "scores": {"class_score": 0.004749298095703125}, "domain": "pixel"}, {"position": {"minX": 506.75, "minY": 181.0, "maxX": 515.0, "maxY": 364.5}, "class_id": 0, "box_caption": "bone-loss 0.005", "scores": {"class_score": 0.00473785400390625}, "domain": "pixel"}, {"position": {"minX": 59.25, "minY": 146.75, "maxX": 619.0, "maxY": 379.75}, "class_id": 0, "box_caption": "bone-loss 0.005", "scores": {"class_score": 0.00473785400390625}, "domain": "pixel"}, {"position": {"minX": 24.875, "minY": 234.375, "maxX": 369.0, "maxY": 344.5}, "class_id": 1, "box_caption": "dental-caries 0.005", "scores": {"class_score": 0.004726409912109375}, "domain": "pixel"}, {"position": {"minX": 229.0, "minY": 353.0, "maxX": 426.0, "maxY": 588.0}, "class_id": 0, "box_caption": "bone-loss 0.005", "scores": {"class_score": 0.00472259521484375}, "domain": "pixel"}, {"position": {"minX": 53.5625, "minY": 148.0, "maxX": 175.25, "maxY": 353.25}, "class_id": 0, "box_caption": "bone-loss 0.005", "scores": {"class_score": 0.0047149658203125}, "domain": "pixel"}, {"position": {"minX": 27.625, "minY": 259.5, "maxX": 364.0, "maxY": 377.0}, "class_id": 1, "box_caption": "dental-caries 0.005", "scores": {"class_score": 0.00470733642578125}, "domain": "pixel"}, {"position": {"minX": 509.25, "minY": 214.625, "maxX": 627.5, "maxY": 597.5}, "class_id": 1, "box_caption": "dental-caries 0.005", "scores": {"class_score": 0.00470733642578125}, "domain": "pixel"}, {"position": {"minX": 1.0, "minY": 352.0, "maxX": 141.0, "maxY": 575.0}, "class_id": 0, "box_caption": "bone-loss 0.005", "scores": {"class_score": 0.004695892333984375}, "domain": "pixel"}, {"position": {"minX": 329.25, "minY": 361.5, "maxX": 455.25, "maxY": 568.5}, "class_id": 1, "box_caption": "dental-caries 0.005", "scores": {"class_score": 0.004688262939453125}, "domain": "pixel"}, {"position": {"minX": 555.0, "minY": 378.5, "maxX": 560.0, "maxY": 590.0}, "class_id": 0, "box_caption": "bone-loss 0.005", "scores": {"class_score": 0.0046844482421875}, "domain": "pixel"}, {"position": {"minX": 211.5, "minY": 305.5, "maxX": 365.0, "maxY": 635.5}, "class_id": 0, "box_caption": "bone-loss 0.005", "scores": {"class_score": 0.0046844482421875}, "domain": "pixel"}, {"position": {"minX": 446.0, "minY": 401.5, "maxX": 451.0, "maxY": 560.5}, "class_id": 0, "box_caption": "bone-loss 0.005", "scores": {"class_score": 0.00467681884765625}, "domain": "pixel"}, {"position": {"minX": 312.75, "minY": 320.75, "maxX": 323.75, "maxY": 356.75}, "class_id": 0, "box_caption": "bone-loss 0.005", "scores": {"class_score": 0.004669189453125}, "domain": "pixel"}, {"position": {"minX": 373.5, "minY": 346.5, "maxX": 403.5, "maxY": 371.5}, "class_id": 1, "box_caption": "dental-caries 0.005", "scores": {"class_score": 0.004650115966796875}, "domain": "pixel"}, {"position": {"minX": 208.5, "minY": 88.625, "maxX": 280.5, "maxY": 340.0}, "class_id": 1, "box_caption": "dental-caries 0.005", "scores": {"class_score": 0.004650115966796875}, "domain": "pixel"}, {"position": {"minX": 311.75, "minY": 391.25, "maxX": 318.75, "maxY": 442.25}, "class_id": 0, "box_caption": "bone-loss 0.005", "scores": {"class_score": 0.004638671875}, "domain": "pixel"}, {"position": {"minX": 331.75, "minY": 218.0, "maxX": 385.75, "maxY": 515.0}, "class_id": 0, "box_caption": "bone-loss 0.005", "scores": {"class_score": 0.004619598388671875}, "domain": "pixel"}, {"position": {"minX": 59.9375, "minY": 212.75, "maxX": 210.75, "maxY": 463.25}, "class_id": 0, "box_caption": "bone-loss 0.005", "scores": {"class_score": 0.004611968994140625}, "domain": "pixel"}, {"position": {"minX": 424.5, "minY": 321.0, "maxX": 425.0, "maxY": 343.0}, "class_id": 0, "box_caption": "bone-loss 0.005", "scores": {"class_score": 0.004608154296875}, "domain": "pixel"}, {"position": {"minX": 45.875, "minY": 192.625, "maxX": 354.5, "maxY": 318.0}, "class_id": 1, "box_caption": "dental-caries 0.005", "scores": {"class_score": 0.004596710205078125}, "domain": "pixel"}, {"position": {"minX": 413.75, "minY": 338.75, "maxX": 414.25, "maxY": 357.25}, "class_id": 0, "box_caption": "bone-loss 0.005", "scores": {"class_score": 0.004589080810546875}, "domain": "pixel"}, {"position": {"minX": 265.0, "minY": 88.125, "maxX": 289.0, "maxY": 404.0}, "class_id": 0, "box_caption": "bone-loss 0.005", "scores": {"class_score": 0.004573822021484375}, "domain": "pixel"}, {"position": {"minX": 47.4375, "minY": 136.0, "maxX": 287.25, "maxY": 299.75}, "class_id": 1, "box_caption": "dental-caries 0.005", "scores": {"class_score": 0.004550933837890625}, "domain": "pixel"}, {"position": {"minX": 466.5, "minY": 348.75, "maxX": 591.5, "maxY": 599.5}, "class_id": 1, "box_caption": "dental-caries 0.005", "scores": {"class_score": 0.004547119140625}, "domain": "pixel"}, {"position": {"minX": 343.5, "minY": 313.5, "maxX": 446.0, "maxY": 330.0}, "class_id": 0, "box_caption": "bone-loss 0.005", "scores": {"class_score": 0.00453948974609375}, "domain": "pixel"}, {"position": {"minX": 310.75, "minY": 297.0, "maxX": 324.25, "maxY": 344.5}, "class_id": 0, "box_caption": "bone-loss 0.005", "scores": {"class_score": 0.00453948974609375}, "domain": "pixel"}, {"position": {"minX": 482.25, "minY": 267.75, "maxX": 528.0, "maxY": 324.25}, "class_id": 1, "box_caption": "dental-caries 0.005", "scores": {"class_score": 0.0045318603515625}, "domain": "pixel"}, {"position": {"minX": 509.25, "minY": 214.625, "maxX": 627.5, "maxY": 597.5}, "class_id": 0, "box_caption": "bone-loss 0.005", "scores": {"class_score": 0.00452423095703125}, "domain": "pixel"}, {"position": {"minX": 175.875, "minY": 206.875, "maxX": 233.375, "maxY": 358.0}, "class_id": 0, "box_caption": "bone-loss 0.005", "scores": {"class_score": 0.004512786865234375}, "domain": "pixel"}, {"position": {"minX": 327.0, "minY": 350.0, "maxX": 336.0, "maxY": 448.5}, "class_id": 0, "box_caption": "bone-loss 0.005", "scores": {"class_score": 0.00450897216796875}, "domain": "pixel"}, {"position": {"minX": 315.5, "minY": 361.75, "maxX": 326.5, "maxY": 438.25}, "class_id": 0, "box_caption": "bone-loss 0.005", "scores": {"class_score": 0.0045013427734375}, "domain": "pixel"}, {"position": {"minX": 430.25, "minY": 292.75, "maxX": 430.75, "maxY": 326.25}, "class_id": 0, "box_caption": "bone-loss 0.004", "scores": {"class_score": 0.004497528076171875}, "domain": "pixel"}, {"position": {"minX": 253.5, "minY": 153.5, "maxX": 293.0, "maxY": 535.5}, "class_id": 1, "box_caption": "dental-caries 0.004", "scores": {"class_score": 0.004497528076171875}, "domain": "pixel"}, {"position": {"minX": 594.5, "minY": 446.75, "maxX": 626.5, "maxY": 488.25}, "class_id": 0, "box_caption": "bone-loss 0.004", "scores": {"class_score": 0.004486083984375}, "domain": "pixel"}, {"position": {"minX": 413.5, "minY": 321.25, "maxX": 510.5, "maxY": 557.0}, "class_id": 0, "box_caption": "bone-loss 0.004", "scores": {"class_score": 0.004482269287109375}, "domain": "pixel"}, {"position": {"minX": 196.75, "minY": 196.125, "maxX": 299.25, "maxY": 353.0}, "class_id": 1, "box_caption": "dental-caries 0.004", "scores": {"class_score": 0.004467010498046875}, "domain": "pixel"}, {"position": {"minX": 465.75, "minY": 240.0, "maxX": 495.25, "maxY": 358.5}, "class_id": 0, "box_caption": "bone-loss 0.004", "scores": {"class_score": 0.00446319580078125}, "domain": "pixel"}, {"position": {"minX": 35.3125, "minY": 79.875, "maxX": 183.75, "maxY": 276.5}, "class_id": 1, "box_caption": "dental-caries 0.004", "scores": {"class_score": 0.004444122314453125}, "domain": "pixel"}, {"position": {"minX": 391.75, "minY": 376.0, "maxX": 516.0, "maxY": 623.5}, "class_id": 1, "box_caption": "dental-caries 0.004", "scores": {"class_score": 0.004444122314453125}, "domain": "pixel"}, {"position": {"minX": 579.0, "minY": 374.0, "maxX": 597.0, "maxY": 432.0}, "class_id": 0, "box_caption": "bone-loss 0.004", "scores": {"class_score": 0.004405975341796875}, "domain": "pixel"}, {"position": {"minX": 485.5, "minY": 325.75, "maxX": 503.5, "maxY": 398.75}, "class_id": 0, "box_caption": "bone-loss 0.004", "scores": {"class_score": 0.00440216064453125}, "domain": "pixel"}, {"position": {"minX": 576.5, "minY": 443.5, "maxX": 616.5, "maxY": 487.5}, "class_id": 0, "box_caption": "bone-loss 0.004", "scores": {"class_score": 0.00439453125}, "domain": "pixel"}, {"position": {"minX": 468.5, "minY": 291.5, "maxX": 522.0, "maxY": 406.5}, "class_id": 0, "box_caption": "bone-loss 0.004", "scores": {"class_score": 0.004367828369140625}, "domain": "pixel"}, {"position": {"minX": 445.75, "minY": 45.5, "maxX": 604.0, "maxY": 304.0}, "class_id": 0, "box_caption": "bone-loss 0.004", "scores": {"class_score": 0.004352569580078125}, "domain": "pixel"}, {"position": {"minX": 18.1875, "minY": -20.625, "maxX": 131.0, "maxY": 270.5}, "class_id": 0, "box_caption": "bone-loss 0.004", "scores": {"class_score": 0.004329681396484375}, "domain": "pixel"}, {"position": {"minX": -42.0, "minY": 45.625, "maxX": 522.5, "maxY": 281.0}, "class_id": 0, "box_caption": "bone-loss 0.004", "scores": {"class_score": 0.004314422607421875}, "domain": "pixel"}, {"position": {"minX": 169.0, "minY": 246.375, "maxX": 235.5, "maxY": 379.5}, "class_id": 1, "box_caption": "dental-caries 0.004", "scores": {"class_score": 0.00431060791015625}, "domain": "pixel"}, {"position": {"minX": 532.5, "minY": 386.25, "maxX": 549.5, "maxY": 443.25}, "class_id": 0, "box_caption": "bone-loss 0.004", "scores": {"class_score": 0.00429534912109375}, "domain": "pixel"}, {"position": {"minX": 339.0, "minY": 184.75, "maxX": 385.0, "maxY": 351.25}, "class_id": 0, "box_caption": "bone-loss 0.004", "scores": {"class_score": 0.004283905029296875}, "domain": "pixel"}, {"position": {"minX": 355.75, "minY": 326.75, "maxX": 426.75, "maxY": 356.75}, "class_id": 0, "box_caption": "bone-loss 0.004", "scores": {"class_score": 0.00428009033203125}, "domain": "pixel"}, {"position": {"minX": 545.0, "minY": 327.25, "maxX": 552.0, "maxY": 404.25}, "class_id": 0, "box_caption": "bone-loss 0.004", "scores": {"class_score": 0.004261016845703125}, "domain": "pixel"}, {"position": {"minX": 63.5, "minY": -208.25, "maxX": 345.25, "maxY": 315.25}, "class_id": 0, "box_caption": "bone-loss 0.004", "scores": {"class_score": 0.0042572021484375}, "domain": "pixel"}, {"position": {"minX": 211.5, "minY": 305.5, "maxX": 365.0, "maxY": 635.5}, "class_id": 1, "box_caption": "dental-caries 0.004", "scores": {"class_score": 0.004238128662109375}, "domain": "pixel"}, {"position": {"minX": -79.875, "minY": 169.0, "maxX": 493.5, "maxY": 448.0}, "class_id": 1, "box_caption": "dental-caries 0.004", "scores": {"class_score": 0.004238128662109375}, "domain": "pixel"}, {"position": {"minX": 558.5, "minY": 112.0, "maxX": 620.5, "maxY": 387.5}, "class_id": 0, "box_caption": "bone-loss 0.004", "scores": {"class_score": 0.00423431396484375}, "domain": "pixel"}, {"position": {"minX": 20.75, "minY": 292.0, "maxX": 133.5, "maxY": 569.0}, "class_id": 1, "box_caption": "dental-caries 0.004", "scores": {"class_score": 0.004222869873046875}, "domain": "pixel"}, {"position": {"minX": 306.5, "minY": 407.0, "maxX": 317.5, "maxY": 466.0}, "class_id": 0, "box_caption": "bone-loss 0.004", "scores": {"class_score": 0.004215240478515625}, "domain": "pixel"}, {"position": {"minX": 543.5, "minY": 85.0, "maxX": 587.5, "maxY": 420.5}, "class_id": 0, "box_caption": "bone-loss 0.004", "scores": {"class_score": 0.004215240478515625}, "domain": "pixel"}, {"position": {"minX": 82.375, "minY": 279.0, "maxX": 195.625, "maxY": 531.5}, "class_id": 0, "box_caption": "bone-loss 0.004", "scores": {"class_score": 0.004215240478515625}, "domain": "pixel"}, {"position": {"minX": 193.25, "minY": 269.0, "maxX": 328.25, "maxY": 669.0}, "class_id": 1, "box_caption": "dental-caries 0.004", "scores": {"class_score": 0.004215240478515625}, "domain": "pixel"}, {"position": {"minX": 526.5, "minY": 338.0, "maxX": 530.5, "maxY": 550.5}, "class_id": 0, "box_caption": "bone-loss 0.004", "scores": {"class_score": 0.00421142578125}, "domain": "pixel"}, {"position": {"minX": 144.375, "minY": 152.375, "maxX": 226.625, "maxY": 340.5}, "class_id": 0, "box_caption": "bone-loss 0.004", "scores": {"class_score": 0.004207611083984375}, "domain": "pixel"}, {"position": {"minX": 392.5, "minY": 229.125, "maxX": 406.0, "maxY": 330.0}, "class_id": 0, "box_caption": "bone-loss 0.004", "scores": {"class_score": 0.004192352294921875}, "domain": "pixel"}, {"position": {"minX": 422.25, "minY": 377.25, "maxX": 492.75, "maxY": 570.5}, "class_id": 0, "box_caption": "bone-loss 0.004", "scores": {"class_score": 0.00418853759765625}, "domain": "pixel"}, {"position": {"minX": 201.5, "minY": 224.625, "maxX": 292.25, "maxY": 392.5}, "class_id": 1, "box_caption": "dental-caries 0.004", "scores": {"class_score": 0.004184722900390625}, "domain": "pixel"}, {"position": {"minX": 93.0625, "minY": 164.625, "maxX": 242.5, "maxY": 508.0}, "class_id": 0, "box_caption": "bone-loss 0.004", "scores": {"class_score": 0.004177093505859375}, "domain": "pixel"}, {"position": {"minX": 414.75, "minY": 262.0, "maxX": 418.75, "maxY": 329.5}, "class_id": 0, "box_caption": "bone-loss 0.004", "scores": {"class_score": 0.00417327880859375}, "domain": "pixel"}, {"position": {"minX": -113.375, "minY": 191.5, "maxX": 448.0, "maxY": 371.5}, "class_id": 1, "box_caption": "dental-caries 0.004", "scores": {"class_score": 0.00417327880859375}, "domain": "pixel"}, {"position": {"minX": -158.875, "minY": -10.375, "maxX": 439.5, "maxY": 295.0}, "class_id": 0, "box_caption": "bone-loss 0.004", "scores": {"class_score": 0.004169464111328125}, "domain": "pixel"}, {"position": {"minX": 253.5, "minY": 153.5, "maxX": 293.0, "maxY": 535.5}, "class_id": 0, "box_caption": "bone-loss 0.004", "scores": {"class_score": 0.0041656494140625}, "domain": "pixel"}, {"position": {"minX": 480.25, "minY": 283.0, "maxX": 662.0, "maxY": 665.0}, "class_id": 0, "box_caption": "bone-loss 0.004", "scores": {"class_score": 0.0041656494140625}, "domain": "pixel"}, {"position": {"minX": 131.75, "minY": 234.25, "maxX": 246.25, "maxY": 499.25}, "class_id": 0, "box_caption": "bone-loss 0.004", "scores": {"class_score": 0.004161834716796875}, "domain": "pixel"}, {"position": {"minX": 131.75, "minY": 234.25, "maxX": 246.25, "maxY": 499.25}, "class_id": 1, "box_caption": "dental-caries 0.004", "scores": {"class_score": 0.00415802001953125}, "domain": "pixel"}, {"position": {"minX": 182.875, "minY": 269.5, "maxX": 228.375, "maxY": 300.5}, "class_id": 0, "box_caption": "bone-loss 0.004", "scores": {"class_score": 0.004146575927734375}, "domain": "pixel"}, {"position": {"minX": 88.1875, "minY": 150.125, "maxX": 144.5, "maxY": 294.5}, "class_id": 0, "box_caption": "bone-loss 0.004", "scores": {"class_score": 0.004146575927734375}, "domain": "pixel"}, {"position": {"minX": 570.5, "minY": 102.875, "maxX": 672.5, "maxY": 385.5}, "class_id": 1, "box_caption": "dental-caries 0.004", "scores": {"class_score": 0.004146575927734375}, "domain": "pixel"}, {"position": {"minX": 67.375, "minY": 179.0, "maxX": 158.375, "maxY": 382.5}, "class_id": 0, "box_caption": "bone-loss 0.004", "scores": {"class_score": 0.004123687744140625}, "domain": "pixel"}, {"position": {"minX": 510.75, "minY": 98.0, "maxX": 599.0, "maxY": 326.0}, "class_id": 1, "box_caption": "dental-caries 0.004", "scores": {"class_score": 0.0041046142578125}, "domain": "pixel"}, {"position": {"minX": 458.5, "minY": 338.25, "maxX": 483.5, "maxY": 357.25}, "class_id": 0, "box_caption": "bone-loss 0.004", "scores": {"class_score": 0.004100799560546875}, "domain": "pixel"}, {"position": {"minX": 324.0, "minY": 341.5, "maxX": 331.5, "maxY": 424.5}, "class_id": 0, "box_caption": "bone-loss 0.004", "scores": {"class_score": 0.004100799560546875}, "domain": "pixel"}, {"position": {"minX": 265.5, "minY": 160.0, "maxX": 275.5, "maxY": 334.25}, "class_id": 0, "box_caption": "bone-loss 0.004", "scores": {"class_score": 0.00409698486328125}, "domain": "pixel"}, {"position": {"minX": -139.625, "minY": 230.75, "maxX": 356.5, "maxY": 438.25}, "class_id": 1, "box_caption": "dental-caries 0.004", "scores": {"class_score": 0.004085540771484375}, "domain": "pixel"}, {"position": {"minX": 586.0, "minY": 450.75, "maxX": 600.0, "maxY": 517.0}, "class_id": 1, "box_caption": "dental-caries 0.004", "scores": {"class_score": 0.00408172607421875}, "domain": "pixel"}, {"position": {"minX": 111.8125, "minY": 297.0, "maxX": 229.5, "maxY": 576.0}, "class_id": 0, "box_caption": "bone-loss 0.004", "scores": {"class_score": 0.004077911376953125}, "domain": "pixel"}, {"position": {"minX": -87.1875, "minY": 13.875, "maxX": 309.5, "maxY": 280.0}, "class_id": 0, "box_caption": "bone-loss 0.004", "scores": {"class_score": 0.004062652587890625}, "domain": "pixel"}, {"position": {"minX": 469.75, "minY": 284.75, "maxX": 509.25, "maxY": 308.25}, "class_id": 1, "box_caption": "dental-caries 0.004", "scores": {"class_score": 0.004055023193359375}, "domain": "pixel"}, {"position": {"minX": 593.5, "minY": 432.5, "maxX": 627.5, "maxY": 475.0}, "class_id": 0, "box_caption": "bone-loss 0.004", "scores": {"class_score": 0.004047393798828125}, "domain": "pixel"}, {"position": {"minX": 199.5, "minY": 115.0625, "maxX": 228.75, "maxY": 318.25}, "class_id": 0, "box_caption": "bone-loss 0.004", "scores": {"class_score": 0.0040435791015625}, "domain": "pixel"}, {"position": {"minX": 343.75, "minY": 339.0, "maxX": 356.75, "maxY": 485.5}, "class_id": 0, "box_caption": "bone-loss 0.004", "scores": {"class_score": 0.0040435791015625}, "domain": "pixel"}, {"position": {"minX": 134.25, "minY": 194.25, "maxX": 397.25, "maxY": 377.25}, "class_id": 1, "box_caption": "dental-caries 0.004", "scores": {"class_score": 0.004032135009765625}, "domain": "pixel"}, {"position": {"minX": 489.0, "minY": -9.625, "maxX": 611.0, "maxY": 309.0}, "class_id": 0, "box_caption": "bone-loss 0.004", "scores": {"class_score": 0.004032135009765625}, "domain": "pixel"}, {"position": {"minX": -30.0, "minY": 88.75, "maxX": 385.5, "maxY": 411.25}, "class_id": 0, "box_caption": "bone-loss 0.004", "scores": {"class_score": 0.004016876220703125}, "domain": "pixel"}, {"position": {"minX": 280.5, "minY": 100.125, "maxX": 343.0, "maxY": 579.5}, "class_id": 1, "box_caption": "dental-caries 0.004", "scores": {"class_score": 0.0040130615234375}, "domain": "pixel"}, {"position": {"minX": 498.0, "minY": 272.25, "maxX": 530.0, "maxY": 416.25}, "class_id": 0, "box_caption": "bone-loss 0.004", "scores": {"class_score": 0.00400543212890625}, "domain": "pixel"}, {"position": {"minX": 297.75, "minY": 120.125, "maxX": 332.25, "maxY": 498.0}, "class_id": 1, "box_caption": "dental-caries 0.004", "scores": {"class_score": 0.00399017333984375}, "domain": "pixel"}, {"position": {"minX": 510.75, "minY": 98.0, "maxX": 599.0, "maxY": 326.0}, "class_id": 0, "box_caption": "bone-loss 0.004", "scores": {"class_score": 0.0039825439453125}, "domain": "pixel"}, {"position": {"minX": 54.46875, "minY": 303.0, "maxX": 169.0, "maxY": 562.5}, "class_id": 1, "box_caption": "dental-caries 0.004", "scores": {"class_score": 0.0039825439453125}, "domain": "pixel"}, {"position": {"minX": 212.75, "minY": 203.5, "maxX": 416.75, "maxY": 426.5}, "class_id": 1, "box_caption": "dental-caries 0.004", "scores": {"class_score": 0.00397491455078125}, "domain": "pixel"}, {"position": {"minX": 66.0625, "minY": 46.125, "maxX": 155.25, "maxY": 270.5}, "class_id": 0, "box_caption": "bone-loss 0.004", "scores": {"class_score": 0.00396728515625}, "domain": "pixel"}, {"position": {"minX": -73.125, "minY": -64.0, "maxX": 177.875, "maxY": 473.5}, "class_id": 1, "box_caption": "dental-caries 0.004", "scores": {"class_score": 0.00392913818359375}, "domain": "pixel"}, {"position": {"minX": 104.5, "minY": 256.75, "maxX": 228.25, "maxY": 554.0}, "class_id": 1, "box_caption": "dental-caries 0.004", "scores": {"class_score": 0.0039215087890625}, "domain": "pixel"}, {"position": {"minX": 34.3125, "minY": 233.625, "maxX": 181.75, "maxY": 437.5}, "class_id": 0, "box_caption": "bone-loss 0.004", "scores": {"class_score": 0.003910064697265625}, "domain": "pixel"}, {"position": {"minX": 280.5, "minY": 100.125, "maxX": 343.0, "maxY": 579.5}, "class_id": 0, "box_caption": "bone-loss 0.004", "scores": {"class_score": 0.0039043426513671875}, "domain": "pixel"}, {"position": {"minX": 388.0, "minY": 397.75, "maxX": 392.5, "maxY": 497.75}, "class_id": 0, "box_caption": "bone-loss 0.004", "scores": {"class_score": 0.0039005279541015625}, "domain": "pixel"}, {"position": {"minX": 626.5, "minY": 135.625, "maxX": 686.5, "maxY": 363.0}, "class_id": 1, "box_caption": "dental-caries 0.004", "scores": {"class_score": 0.0038967132568359375}, "domain": "pixel"}, {"position": {"minX": 187.0, "minY": 290.25, "maxX": 241.25, "maxY": 311.25}, "class_id": 0, "box_caption": "bone-loss 0.004", "scores": {"class_score": 0.0038890838623046875}, "domain": "pixel"}, {"position": {"minX": 169.0, "minY": 246.375, "maxX": 235.5, "maxY": 379.5}, "class_id": 0, "box_caption": "bone-loss 0.004", "scores": {"class_score": 0.0038890838623046875}, "domain": "pixel"}, {"position": {"minX": 378.25, "minY": 298.25, "maxX": 441.75, "maxY": 312.25}, "class_id": 0, "box_caption": "bone-loss 0.004", "scores": {"class_score": 0.003879547119140625}, "domain": "pixel"}, {"position": {"minX": 434.25, "minY": 372.5, "maxX": 442.25, "maxY": 465.0}, "class_id": 0, "box_caption": "bone-loss 0.004", "scores": {"class_score": 0.0038776397705078125}, "domain": "pixel"}, {"position": {"minX": 220.625, "minY": 390.75, "maxX": 244.625, "maxY": 455.25}, "class_id": 0, "box_caption": "bone-loss 0.004", "scores": {"class_score": 0.0038700103759765625}, "domain": "pixel"}, {"position": {"minX": 331.25, "minY": 345.75, "maxX": 368.75, "maxY": 369.75}, "class_id": 0, "box_caption": "bone-loss 0.004", "scores": {"class_score": 0.0038661956787109375}, "domain": "pixel"}, {"position": {"minX": 193.25, "minY": 269.0, "maxX": 328.25, "maxY": 669.0}, "class_id": 0, "box_caption": "bone-loss 0.004", "scores": {"class_score": 0.0038604736328125}, "domain": "pixel"}, {"position": {"minX": 501.25, "minY": 298.25, "maxX": 515.5, "maxY": 371.25}, "class_id": 1, "box_caption": "dental-caries 0.004", "scores": {"class_score": 0.003856658935546875}, "domain": "pixel"}, {"position": {"minX": -139.625, "minY": 230.75, "maxX": 356.5, "maxY": 438.25}, "class_id": 0, "box_caption": "bone-loss 0.004", "scores": {"class_score": 0.0038547515869140625}, "domain": "pixel"}, {"position": {"minX": 55.15625, "minY": 308.25, "maxX": 145.5, "maxY": 373.75}, "class_id": 1, "box_caption": "dental-caries 0.004", "scores": {"class_score": 0.00385284423828125}, "domain": "pixel"}, {"position": {"minX": 238.25, "minY": 0.5, "maxX": 313.25, "maxY": 363.25}, "class_id": 1, "box_caption": "dental-caries 0.004", "scores": {"class_score": 0.0038471221923828125}, "domain": "pixel"}, {"position": {"minX": 578.0, "minY": 49.875, "maxX": 669.0, "maxY": 300.0}, "class_id": 1, "box_caption": "dental-caries 0.004", "scores": {"class_score": 0.0038433074951171875}, "domain": "pixel"}, {"position": {"minX": 434.5, "minY": 74.75, "maxX": 502.0, "maxY": 464.75}, "class_id": 0, "box_caption": "bone-loss 0.004", "scores": {"class_score": 0.003841400146484375}, "domain": "pixel"}, {"position": {"minX": 470.25, "minY": 330.5, "maxX": 507.25, "maxY": 368.0}, "class_id": 1, "box_caption": "dental-caries 0.004", "scores": {"class_score": 0.003833770751953125}, "domain": "pixel"}, {"position": {"minX": 371.5, "minY": 319.0, "maxX": 444.5, "maxY": 362.0}, "class_id": 1, "box_caption": "dental-caries 0.004", "scores": {"class_score": 0.003833770751953125}, "domain": "pixel"}, {"position": {"minX": 255.75, "minY": -30.375, "maxX": 351.25, "maxY": 390.0}, "class_id": 1, "box_caption": "dental-caries 0.004", "scores": {"class_score": 0.0038280487060546875}, "domain": "pixel"}, {"position": {"minX": 347.5, "minY": 108.0, "maxX": 461.5, "maxY": 498.5}, "class_id": 0, "box_caption": "bone-loss 0.004", "scores": {"class_score": 0.00382232666015625}, "domain": "pixel"}, {"position": {"minX": 78.5625, "minY": 293.5, "maxX": 209.0, "maxY": 581.0}, "class_id": 1, "box_caption": "dental-caries 0.004", "scores": {"class_score": 0.00382232666015625}, "domain": "pixel"}, {"position": {"minX": 192.5, "minY": 16.875, "maxX": 348.5, "maxY": 221.875}, "class_id": 1, "box_caption": "dental-caries 0.004", "scores": {"class_score": 0.003810882568359375}, "domain": "pixel"}, {"position": {"minX": 558.5, "minY": 112.0, "maxX": 620.5, "maxY": 387.5}, "class_id": 1, "box_caption": "dental-caries 0.004", "scores": {"class_score": 0.003810882568359375}, "domain": "pixel"}, {"position": {"minX": 398.5, "minY": 268.5, "maxX": 404.5, "maxY": 322.0}, "class_id": 0, "box_caption": "bone-loss 0.004", "scores": {"class_score": 0.0037994384765625}, "domain": "pixel"}, {"position": {"minX": 471.25, "minY": 340.5, "maxX": 489.75, "maxY": 386.5}, "class_id": 0, "box_caption": "bone-loss 0.004", "scores": {"class_score": 0.00379180908203125}, "domain": "pixel"}, {"position": {"minX": 376.75, "minY": 220.0, "maxX": 388.75, "maxY": 338.5}, "class_id": 0, "box_caption": "bone-loss 0.004", "scores": {"class_score": 0.0037822723388671875}, "domain": "pixel"}, {"position": {"minX": 50.1875, "minY": 84.375, "maxX": 98.4375, "maxY": 291.0}, "class_id": 0, "box_caption": "bone-loss 0.004", "scores": {"class_score": 0.0037784576416015625}, "domain": "pixel"}, {"position": {"minX": 189.75, "minY": 9.125, "maxX": 284.5, "maxY": 289.5}, "class_id": 0, "box_caption": "bone-loss 0.004", "scores": {"class_score": 0.0037670135498046875}, "domain": "pixel"}, {"position": {"minX": 84.875, "minY": 271.25, "maxX": 372.0, "maxY": 422.75}, "class_id": 1, "box_caption": "dental-caries 0.004", "scores": {"class_score": 0.003765106201171875}, "domain": "pixel"}, {"position": {"minX": 96.75, "minY": 91.625, "maxX": 700.0, "maxY": 443.0}, "class_id": 0, "box_caption": "bone-loss 0.004", "scores": {"class_score": 0.003765106201171875}, "domain": "pixel"}, {"position": {"minX": 35.25, "minY": 177.875, "maxX": 755.0, "maxY": 550.0}, "class_id": 0, "box_caption": "bone-loss 0.004", "scores": {"class_score": 0.00376129150390625}, "domain": "pixel"}], "class_labels": {"0": "bone-loss", "1": "dental-caries"}}